donkit/embeddings/__init__.py
donkit/embeddings/azure_openai_embeddings.py
donkit/embeddings/custom_embeddings.py
donkit/embeddings/donkit_embeddings.py
donkit/embeddings/llm_gate_embeddings.py
donkit/embeddings/ollama_embeddings.py
donkit/embeddings/openai_embedder.py
donkit/embeddings/vertex_embeddings.py
donkit_embeddings-0.1.10.dist-info/METADATA
donkit_embeddings-0.1.10.dist-info/WHEEL
donkit_embeddings-0.1.10.dist-info/RECORD
