Metadata-Version: 2.3
Name: donkit-embeddings
Version: 0.1.10
Summary: Custom embeddings implementations for Donkit RagOps
License: MIT
Author: Donkit AI
Author-email: opensource@donkit.ai
Requires-Python: >=3.12,<3.14
Classifier: License :: OSI Approved :: MIT License
Classifier: Programming Language :: Python :: 3
Classifier: Programming Language :: Python :: 3.12
Classifier: Programming Language :: Python :: 3.13
Requires-Dist: donkit-llm (>=0.1.5,<0.2.0)
Requires-Dist: google-genai (>=1.38.0,<2.0.0)
Requires-Dist: langchain-core (>=0.3.79,<0.4.0)
Requires-Dist: ollama (>=0.6.0,<0.7.0)
Requires-Dist: openai (>=2.1.0,<3.0.0)
